fact_sphere/__about__.py
fact_sphere/__init__.py
fact_sphere/api.py
fact_sphere/facts/__init__.py
fact_sphere/facts/audio/false_01.wav
fact_sphere/facts/audio/false_02.wav
fact_sphere/facts/audio/false_03.wav
fact_sphere/facts/audio/false_04.wav
fact_sphere/facts/audio/false_05.wav
fact_sphere/facts/audio/false_06.wav
fact_sphere/facts/audio/false_07.wav
fact_sphere/facts/audio/false_08.wav
fact_sphere/facts/audio/false_09.wav
fact_sphere/facts/audio/false_10.wav
fact_sphere/facts/audio/false_11.wav
fact_sphere/facts/audio/false_12.wav
fact_sphere/facts/audio/false_13.wav
fact_sphere/facts/audio/false_14.wav
fact_sphere/facts/audio/false_15.wav
fact_sphere/facts/audio/false_16.wav
fact_sphere/facts/audio/false_17.wav
fact_sphere/facts/audio/false_18.wav
fact_sphere/facts/audio/false_19.wav
fact_sphere/facts/audio/false_20.wav
fact_sphere/facts/audio/false_21.wav
fact_sphere/facts/audio/false_22.wav
fact_sphere/facts/audio/false_23.wav
fact_sphere/facts/audio/false_24.wav
fact_sphere/facts/audio/false_25.wav
fact_sphere/facts/audio/nearly_true_01.wav
fact_sphere/facts/audio/nearly_true_02.wav
fact_sphere/facts/audio/nearly_true_03.wav
fact_sphere/facts/audio/nearly_true_04.wav
fact_sphere/facts/audio/nearly_true_05.wav
fact_sphere/facts/audio/nearly_true_06.wav
fact_sphere/facts/audio/nearly_true_07.wav
fact_sphere/facts/audio/nearly_true_08.wav
fact_sphere/facts/audio/nearly_true_09.wav
fact_sphere/facts/audio/not_facts_01.wav
fact_sphere/facts/audio/not_facts_02.wav
fact_sphere/facts/audio/not_facts_03.wav
fact_sphere/facts/audio/not_facts_04.wav
fact_sphere/facts/audio/not_facts_05.wav
fact_sphere/facts/audio/not_facts_06.wav
fact_sphere/facts/audio/not_facts_07.wav
fact_sphere/facts/audio/partially_true_01.wav
fact_sphere/facts/audio/partially_true_02.wav
fact_sphere/facts/audio/partially_true_03.wav
fact_sphere/facts/audio/partially_true_04.wav
fact_sphere/facts/audio/partially_true_05.wav
fact_sphere/facts/audio/partially_true_06.wav
fact_sphere-1.0.1.dist-info/LICENSE
fact_sphere-1.0.1.dist-info/WHEEL
fact_sphere-1.0.1.dist-info/METADATA
fact_sphere-1.0.1.dist-info/RECORD
